playsongs/__init__.py
playsongs/__main__.py
playsongs-2024.1.0.0.dist-info/METADATA
playsongs-2024.1.0.0.dist-info/WHEEL
playsongs-2024.1.0.0.dist-info/RECORD
