Metadata-Version: 2.1
Name: PlaySongs
Version: 2024.1.0.0
Summary: Play MP3 files from a directory.
Home-page: https://gitlab.com/fer1035_python/modules/pypi-playsongs
License: GPL-2.0-only
Keywords: music,MP3
Author: Ahmad Ferdaus Abd Razak
Author-email: ahmad.ferdaus.abd.razak@ni.com
Requires-Python: >=3.8,<4.0
Classifier: License :: OSI Approved :: GNU General Public License v2 (GPLv2)
Classifier: Programming Language :: Python :: 3
Classifier: Programming Language :: Python :: 3.8
Classifier: Programming Language :: Python :: 3.9
Classifier: Programming Language :: Python :: 3.10
Classifier: Programming Language :: Python :: 3.11
Classifier: Programming Language :: Python :: 3.12
Requires-Dist: playsound (>=1.3.0,<2.0.0)
Requires-Dist: pyobjc (>=9.0,<10.0)
Project-URL: Repository, https://gitlab.com/fer1035_python/modules/pypi-playsongs
